strictify.py
strictify-0.1.1.dist-info/WHEEL
strictify-0.1.1.dist-info/METADATA
strictify-0.1.1.dist-info/RECORD
