Metadata-Version: 2.1
Name: strictify
Version: 0.1.1
Summary: A strict decorator for python
Author: Mikhail
Author-email: joinmma@gmail.com
Requires-Python: >=3.6,<4.0
Classifier: Programming Language :: Python :: 3
Classifier: Programming Language :: Python :: 3.6
Classifier: Programming Language :: Python :: 3.7
Classifier: Programming Language :: Python :: 3.8
Classifier: Programming Language :: Python :: 3.9
